slskd_api/__init__.py
slskd_api/client.py
slskd_api/apis/__init__.py
slskd_api/apis/_base.py
slskd_api/apis/_types.py
slskd_api/apis/application.py
slskd_api/apis/conversations.py
slskd_api/apis/events.py
slskd_api/apis/files.py
slskd_api/apis/logs.py
slskd_api/apis/options.py
slskd_api/apis/relay.py
slskd_api/apis/rooms.py
slskd_api/apis/searches.py
slskd_api/apis/server.py
slskd_api/apis/session.py
slskd_api/apis/shares.py
slskd_api/apis/telemetry.py
slskd_api/apis/transfers.py
slskd_api/apis/users.py
slskd_api-0.2.1.dist-info/licenses/LICENSE.md
slskd_api-0.2.1.dist-info/METADATA
slskd_api-0.2.1.dist-info/WHEEL
slskd_api-0.2.1.dist-info/top_level.txt
slskd_api-0.2.1.dist-info/RECORD
