Metadata-Version: 2.4
Name: slskd-api
Version: 0.2.1
Summary: API Wrapper to interact with slskd
Author: bigoulours
License: GNU Affero General Public License v3.0
Project-URL: Documentation, https://slskd-api.readthedocs.io
Project-URL: Source, https://github.com/bigoulours/slskd-python-api
Project-URL: Funding, https://liberapay.com/bigoulours/donate
Requires-Python: >=3.7
License-File: LICENSE.md
Requires-Dist: requests>=2.25.1
Dynamic: author
Dynamic: description
Dynamic: description-content-type
Dynamic: license
Dynamic: license-file
Dynamic: project-url
Dynamic: requires-dist
Dynamic: requires-python
Dynamic: summary
